shifty_face/__init__.py
shifty_face/shiftyface.py
shiftyface-0.4.1.dist-info/LICENSE.txt
shiftyface-0.4.1.dist-info/METADATA
shiftyface-0.4.1.dist-info/WHEEL
shiftyface-0.4.1.dist-info/top_level.txt
shiftyface-0.4.1.dist-info/RECORD
