Metadata-Version: 2.1
Name: shiftyface
Version: 0.4.1
Summary: UNKNOWN
Home-page: https://github.com/rpupkin77/shiftyface
Author: Paul Thompson
Author-email: pt@sevenelm.com
License: MIT
Keywords: nft,rarity,image generation,eth,collection generator
Platform: UNKNOWN
Requires-Dist: Pillow
